pyreclaim-0.4.0.dist-info/licenses/LICENSE
reclaim/__init__.py
reclaim/generate_features.py
reclaim/reclaim.py
reclaim/derived_features/__init__.py
reclaim/derived_features/feature_engineering_and_transformation.py
reclaim/dynamic_features/__init__.py
reclaim/dynamic_features/catchment_dynamic.py
reclaim/dynamic_features/reservoir_dynamic.py
reclaim/dynamic_features/utils/__init__.py
reclaim/dynamic_features/utils/catchment_meteorology.py
reclaim/dynamic_features/utils/inflow_outflow.py
reclaim/dynamic_features/utils/rainfall.py
reclaim/dynamic_features/utils/statistical_metrics.py
reclaim/dynamic_features/utils/ts_aggregate.py
reclaim/static_features/__init__.py
reclaim/static_features/catchment_static.py
reclaim/static_features/reservoir_static.py
reclaim/static_features/utils/__init__.py
reclaim/static_features/utils/aec_shape.py
reclaim/static_features/utils/area_perimeter.py
reclaim/static_features/utils/catchment_agreggate.py
reclaim/static_features/utils/flow_length.py
pyreclaim-0.4.0.dist-info/METADATA
pyreclaim-0.4.0.dist-info/WHEEL
pyreclaim-0.4.0.dist-info/top_level.txt
pyreclaim-0.4.0.dist-info/RECORD
