Metadata-Version: 2.4
Name: pyreclaim
Version: 0.4.0
Summary: Reservoir Estimation of Capacity Loss using AI based Methods
Author-email: Sanchit Minocha <msanchit@uw.edu>
License:                     GNU GENERAL PUBLIC LICENSE
Project-URL: Homepage, https://github.com/UW-SASWE/RECLAIM
Project-URL: Bug Tracker, https://github.com/UW-SASWE/RECLAIM/issues
Classifier: Programming Language :: Python :: 3
Classifier: License :: OSI Approved :: MIT License
Requires-Python: >=3.6
License-File: LICENSE
Requires-Dist: numpy
Requires-Dist: pandas
Requires-Dist: geopandas
Requires-Dist: networkx
Requires-Dist: shapely
Requires-Dist: regionmask
Requires-Dist: xarray
Requires-Dist: scipy
Requires-Dist: scikit-learn
Requires-Dist: joblib
Requires-Dist: xgboost
Requires-Dist: lightgbm
Requires-Dist: catboost
Requires-Dist: openpyxl
Requires-Dist: netcdf4
Requires-Dist: dask
Requires-Dist: rioxarray
Dynamic: license-file
